odoo/addons/fleet_vehicle_inspection_item_compatible_product/README.rst
odoo/addons/fleet_vehicle_inspection_item_compatible_product/__init__.py
odoo/addons/fleet_vehicle_inspection_item_compatible_product/__manifest__.py
odoo/addons/fleet_vehicle_inspection_item_compatible_product/i18n/fleet_vehicle_inspection_item_compatible_product.pot
odoo/addons/fleet_vehicle_inspection_item_compatible_product/i18n/it.po
odoo/addons/fleet_vehicle_inspection_item_compatible_product/i18n/pt_BR.po
odoo/addons/fleet_vehicle_inspection_item_compatible_product/models/__init__.py
odoo/addons/fleet_vehicle_inspection_item_compatible_product/models/fleet_vehicle_inspection_item.py
odoo/addons/fleet_vehicle_inspection_item_compatible_product/models/product_product.py
odoo/addons/fleet_vehicle_inspection_item_compatible_product/readme/CONFIGURE.rst
odoo/addons/fleet_vehicle_inspection_item_compatible_product/readme/CONTRIBUTORS.rst
odoo/addons/fleet_vehicle_inspection_item_compatible_product/readme/CREDITS.rst
odoo/addons/fleet_vehicle_inspection_item_compatible_product/readme/DESCRIPTION.rst
odoo/addons/fleet_vehicle_inspection_item_compatible_product/readme/ROADMAP.rst
odoo/addons/fleet_vehicle_inspection_item_compatible_product/static/description/banner.png
odoo/addons/fleet_vehicle_inspection_item_compatible_product/static/description/icon.png
odoo/addons/fleet_vehicle_inspection_item_compatible_product/static/description/index.html
odoo/addons/fleet_vehicle_inspection_item_compatible_product/views/fleet_vehicle_inspection_item.xml
odoo/addons/fleet_vehicle_inspection_item_compatible_product/views/product_product.xml
odoo12_addon_fleet_vehicle_inspection_item_compatible_product-12.0.1.0.0.99.dev8.dist-info/METADATA
odoo12_addon_fleet_vehicle_inspection_item_compatible_product-12.0.1.0.0.99.dev8.dist-info/WHEEL
odoo12_addon_fleet_vehicle_inspection_item_compatible_product-12.0.1.0.0.99.dev8.dist-info/top_level.txt
odoo12_addon_fleet_vehicle_inspection_item_compatible_product-12.0.1.0.0.99.dev8.dist-info/RECORD
